cell_tracking_BC/produce-gt-from-dn.py
cell_tracking_BC/track_finder.py
cell_tracking_BC/catalog/parser.py
cell_tracking_BC/catalog/channel/ratio.py
cell_tracking_BC/catalog/feature/geometrical/dummy.py
cell_tracking_BC/catalog/feature/radiometric/entropy.py
cell_tracking_BC/catalog/feature/set/numpy_.py
cell_tracking_BC/catalog/feature/set/skimage_.py
cell_tracking_BC/catalog/feature/temporal/shift.py
cell_tracking_BC/catalog/matching/jaccard.py
cell_tracking_BC/catalog/processing/background.py
cell_tracking_BC/catalog/processing/contrast.py
cell_tracking_BC/catalog/processing/geometry.py
cell_tracking_BC/catalog/processing/registration.py
cell_tracking_BC/catalog/segmentation/tf_network.py
cell_tracking_BC/catalog/tracking/gmb_tracker.py
cell_tracking_BC/in_out/file/divisions.py
cell_tracking_BC/in_out/file/event.py
cell_tracking_BC/in_out/file/feature.py
cell_tracking_BC/in_out/file/feature_book.py
cell_tracking_BC/in_out/file/load.py
cell_tracking_BC/in_out/file/path.py
cell_tracking_BC/in_out/file/track.py
cell_tracking_BC/in_out/file/table/cell.py
cell_tracking_BC/in_out/file/table/chart.py
cell_tracking_BC/in_out/file/table/column.py
cell_tracking_BC/in_out/file/table/sheet.py
cell_tracking_BC/in_out/graphics/annotations.py
cell_tracking_BC/in_out/graphics/event.py
cell_tracking_BC/in_out/graphics/feature.py
cell_tracking_BC/in_out/graphics/segmentation.py
cell_tracking_BC/in_out/graphics/sequence.py
cell_tracking_BC/in_out/graphics/tracking.py
cell_tracking_BC/in_out/graphics/dbe/matplotlib/context.py
cell_tracking_BC/in_out/graphics/dbe/matplotlib/d_2.py
cell_tracking_BC/in_out/graphics/dbe/matplotlib/d_3.py
cell_tracking_BC/in_out/graphics/dbe/matplotlib/d_any.py
cell_tracking_BC/in_out/graphics/dbe/matplotlib/event.py
cell_tracking_BC/in_out/graphics/dbe/matplotlib/style.py
cell_tracking_BC/in_out/graphics/dbe/vedo/context.py
cell_tracking_BC/in_out/graphics/dbe/vedo/d_3.py
cell_tracking_BC/in_out/graphics/dbe/vedo/d_any.py
cell_tracking_bc-2025.1.dist-info/METADATA
cell_tracking_bc-2025.1.dist-info/WHEEL
cell_tracking_bc-2025.1.dist-info/entry_points.txt
cell_tracking_bc-2025.1.dist-info/top_level.txt
cell_tracking_bc-2025.1.dist-info/RECORD
