Metadata-Version: 2.4
Name: cell-tracking-bc
Version: 2025.1
Summary: Base Classes for Cell Tracking in Microscopy
Home-page: https://src.koda.cnrs.fr/eric.debreuve/cell-tracking-bc
Author: Eric Debreuve
Author-email: eric.debreuve@univ-cotedazur.fr
License: CeCILL-2.1
Project-URL: Documentation, https://src.koda.cnrs.fr/eric.debreuve/cell-tracking-bc
Project-URL: Source, https://src.koda.cnrs.fr/eric.debreuve/cell-tracking-bc
Keywords: cell,tracking,microscopy,classes
Classifier: Topic :: Scientific/Engineering :: Image Recognition
Classifier: Intended Audience :: Science/Research
Classifier: License :: OSI Approved :: CEA CNRS Inria Logiciel Libre License, version 2.1 (CeCILL-2.1)
Classifier: Programming Language :: Python :: 3.10
Classifier: Development Status :: 4 - Beta
Requires-Python: >=3.10
Requires-Dist: imageio
Requires-Dist: issue-manager
Requires-Dist: json-any
Requires-Dist: logger-36
Requires-Dist: matplotlib
Requires-Dist: mrc
Requires-Dist: networkx
Requires-Dist: numpy
Requires-Dist: openpyxl
Requires-Dist: pandas
Requires-Dist: pca-b-stream
Requires-Dist: Pillow
Requires-Dist: plotext
Requires-Dist: rich
Requires-Dist: scikit-image
Requires-Dist: scipy
Requires-Dist: tensorflow
Requires-Dist: tensorrt
Requires-Dist: tifffile
Requires-Dist: xlsxwriter
Dynamic: author
Dynamic: author-email
Dynamic: classifier
Dynamic: description
Dynamic: description-content-type
Dynamic: home-page
Dynamic: keywords
Dynamic: license
Dynamic: project-url
Dynamic: requires-dist
Dynamic: requires-python
Dynamic: summary
